pyWorkflowRevealjs/__init__.py
pyWorkflowRevealjs/generator.py
pyWorkflowRevealjs/slidesToWorkflow.py
pyWorkflowRevealjs/workflowToPresentation.py
tests/__init__.py
tests/test_generator.py
pyWorkflowRevealjs-1.0.dist-info/METADATA
pyWorkflowRevealjs-1.0.dist-info/WHEEL
pyWorkflowRevealjs-1.0.dist-info/top_level.txt
pyWorkflowRevealjs-1.0.dist-info/RECORD
